[
  {
    "Id":1, "Rewards":[
      {
        "ThingId":130011, "ThingType":"Item", "ThingQuantity":50
      },
      {
        "ThingId":144001, "ThingType":"Item", "ThingQuantity":50
      },
      {
        "ThingId":110002, "ThingType":"Item", "ThingQuantity":1
      },
      {
        "ThingId":130041, "ThingType":"Item", "ThingQuantity":100
      },
      {
        "ThingId":130042, "ThingType":"Item", "ThingQuantity":50
      }
    ]
  },
  {
    "Id":2, "Rewards":[
      {
        "ThingId":130011, "ThingType":"Item", "ThingQuantity":50
      },
      {
        "ThingId":144001, "ThingType":"Item", "ThingQuantity":50
      },
      {
        "ThingId":110002, "ThingType":"Item", "ThingQuantity":1
      },
      {
        "ThingId":130061, "ThingType":"Item", "ThingQuantity":100
      }
    ]
  },
  {
    "Id":3, "Rewards":[
      {
        "ThingId":130011, "ThingType":"Item", "ThingQuantity":50
      },
      {
        "ThingId":144001, "ThingType":"Item", "ThingQuantity":50
      },
      {
        "ThingId":110002, "ThingType":"Item", "ThingQuantity":1
      },
      {
        "ThingId":130062, "ThingType":"Item", "ThingQuantity":100
      }
    ]
  },
  {
    "Id":4, "Rewards":[
      {
        "ThingId":130011, "ThingType":"Item", "ThingQuantity":50
      },
      {
        "ThingId":144001, "ThingType":"Item", "ThingQuantity":50
      },
      {
        "ThingId":110002, "ThingType":"Item", "ThingQuantity":1
      },
      {
        "ThingId":130063, "ThingType":"Item", "ThingQuantity":100
      }
    ]
  },
  {
    "Id":5, "Rewards":[
      {
        "ThingId":130011, "ThingType":"Item", "ThingQuantity":100
      },
      {
        "ThingId":0, "ThingType":"Jewel", "ThingQuantity":100
      },
      {
        "ThingId":130051, "ThingType":"Item", "ThingQuantity":10
      },
      {
        "ThingId":510003, "ThingType":"Item", "ThingQuantity":1
      },
      {
        "ThingId":144001, "ThingType":"Item", "ThingQuantity":50
      }
    ]
  },
  {
    "Id":6, "Rewards":[
      {
        "ThingId":130011, "ThingType":"Item", "ThingQuantity":50
      },
      {
        "ThingId":110002, "ThingType":"Item", "ThingQuantity":1
      },
      {
        "ThingId":130041, "ThingType":"Item", "ThingQuantity":100
      },
      {
        "ThingId":130042, "ThingType":"Item", "ThingQuantity":50
      }
    ]
  },
  {
    "Id":7, "Rewards":[
      {
        "ThingId":130011, "ThingType":"Item", "ThingQuantity":50
      },
      {
        "ThingId":110002, "ThingType":"Item", "ThingQuantity":1
      },
      {
        "ThingId":130061, "ThingType":"Item", "ThingQuantity":100
      }
    ]
  },
  {
    "Id":8, "Rewards":[
      {
        "ThingId":130011, "ThingType":"Item", "ThingQuantity":50
      },
      {
        "ThingId":110002, "ThingType":"Item", "ThingQuantity":1
      },
      {
        "ThingId":130062, "ThingType":"Item", "ThingQuantity":100
      }
    ]
  },
  {
    "Id":9, "Rewards":[
      {
        "ThingId":130011, "ThingType":"Item", "ThingQuantity":50
      },
      {
        "ThingId":110002, "ThingType":"Item", "ThingQuantity":1
      },
      {
        "ThingId":130063, "ThingType":"Item", "ThingQuantity":100
      }
    ]
  },
  {
    "Id":10, "Rewards":[
      {
        "ThingId":130011, "ThingType":"Item", "ThingQuantity":100
      },
      {
        "ThingId":0, "ThingType":"Jewel", "ThingQuantity":100
      },
      {
        "ThingId":130051, "ThingType":"Item", "ThingQuantity":10
      },
      {
        "ThingId":510003, "ThingType":"Item", "ThingQuantity":1
      }
    ]
  },
  {
    "Id":11, "Rewards":[
      {
        "ThingId":130011, "ThingType":"Item", "ThingQuantity":100
      },
      {
        "ThingId":610001, "ThingType":"Item", "ThingQuantity":1
      },
      {
        "ThingId":140000, "ThingType":"Item", "ThingQuantity":10
      }
    ]
  },
  {
    "Id":12, "Rewards":[
      {
        "ThingId":130011, "ThingType":"Item", "ThingQuantity":200
      },
      {
        "ThingId":610001, "ThingType":"Item", "ThingQuantity":1
      },
      {
        "ThingId":220101, "ThingType":"Item", "ThingQuantity":1
      },
      {
        "ThingId":510004, "ThingType":"Item", "ThingQuantity":1
      },
      {
        "ThingId":130064, "ThingType":"Item", "ThingQuantity":100
      }
    ]
  },
  {
    "Id":13, "Rewards":[
      {
        "ThingId":130011, "ThingType":"Item", "ThingQuantity":200
      },
      {
        "ThingId":610001, "ThingType":"Item", "ThingQuantity":1
      },
      {
        "ThingId":221101, "ThingType":"Item", "ThingQuantity":1
      },
      {
        "ThingId":510004, "ThingType":"Item", "ThingQuantity":1
      },
      {
        "ThingId":130064, "ThingType":"Item", "ThingQuantity":100
      }
    ]
  },
  {
    "Id":14, "Rewards":[
      {
        "ThingId":130011, "ThingType":"Item", "ThingQuantity":200
      },
      {
        "ThingId":610001, "ThingType":"Item", "ThingQuantity":1
      },
      {
        "ThingId":510004, "ThingType":"Item", "ThingQuantity":2
      },
      {
        "ThingId":130064, "ThingType":"Item", "ThingQuantity":100
      }
    ]
  },
  {
    "Id":15, "Rewards":[
      {
        "ThingId":130012, "ThingType":"Item", "ThingQuantity":50
      },
      {
        "ThingId":0, "ThingType":"Jewel", "ThingQuantity":200
      },
      {
        "ThingId":140000, "ThingType":"Item", "ThingQuantity":100
      }
    ]
  }
]