[
  {
    "Id":101, "CircleEventMasterId":1, "Point":1000, "ThingType":"Item", "ThingId":130062, "ThingQuantity":50, "Order":0
  },
  {
    "Id":102, "CircleEventMasterId":1, "Point":5000, "ThingType":"Item", "ThingId":110001, "ThingQuantity":3, "Order":0
  },
  {
    "Id":103, "CircleEventMasterId":1, "Point":10000, "ThingType":"Item", "ThingId":130041, "ThingQuantity":50, "Order":0
  },
  {
    "Id":104, "CircleEventMasterId":1, "Point":15000, "ThingType":"Item", "ThingId":120002, "ThingQuantity":100, "Order":0
  },
  {
    "Id":105, "CircleEventMasterId":1, "Point":20000, "ThingType":"Item", "ThingId":130062, "ThingQuantity":50, "Order":0
  },
  {
    "Id":106, "CircleEventMasterId":1, "Point":25000, "ThingType":"Item", "ThingId":110001, "ThingQuantity":3, "Order":0
  },
  {
    "Id":107, "CircleEventMasterId":1, "Point":30000, "ThingType":"Item", "ThingId":140000, "ThingQuantity":100, "Order":0
  },
  {
    "Id":108, "CircleEventMasterId":1, "Point":35000, "ThingType":"Item", "ThingId":130041, "ThingQuantity":100, "Order":0
  },
  {
    "Id":109, "CircleEventMasterId":1, "Point":40000, "ThingType":"Item", "ThingId":130051, "ThingQuantity":2, "Order":0
  },
  {
    "Id":110, "CircleEventMasterId":1, "Point":45000, "ThingType":"Item", "ThingId":130062, "ThingQuantity":100, "Order":0
  },
  {
    "Id":111, "CircleEventMasterId":1, "Point":50000, "ThingType":"Item", "ThingId":120002, "ThingQuantity":100, "Order":0
  },
  {
    "Id":112, "CircleEventMasterId":1, "Point":60000, "ThingType":"Item", "ThingId":110001, "ThingQuantity":4, "Order":0
  },
  {
    "Id":113, "CircleEventMasterId":1, "Point":70000, "ThingType":"Coin", "ThingId":0, "ThingQuantity":20000, "Order":0
  },
  {
    "Id":114, "CircleEventMasterId":1, "Point":80000, "ThingType":"Item", "ThingId":130051, "ThingQuantity":3, "Order":0
  },
  {
    "Id":115, "CircleEventMasterId":1, "Point":90000, "ThingType":"Item", "ThingId":140000, "ThingQuantity":100, "Order":0
  },
  {
    "Id":116, "CircleEventMasterId":1, "Point":100000, "ThingType":"Item", "ThingId":130062, "ThingQuantity":100, "Order":0
  },
  {
    "Id":117, "CircleEventMasterId":1, "Point":110000, "ThingType":"Item", "ThingId":120002, "ThingQuantity":150, "Order":0
  },
  {
    "Id":118, "CircleEventMasterId":1, "Point":120000, "ThingType":"Item", "ThingId":130041, "ThingQuantity":100, "Order":0
  },
  {
    "Id":119, "CircleEventMasterId":1, "Point":130000, "ThingType":"Item", "ThingId":120003, "ThingQuantity":50, "Order":0
  },
  {
    "Id":120, "CircleEventMasterId":1, "Point":140000, "ThingType":"Item", "ThingId":130042, "ThingQuantity":50, "Order":0
  },
  {
    "Id":121, "CircleEventMasterId":1, "Point":150000, "ThingType":"Item", "ThingId":140000, "ThingQuantity":100, "Order":0
  },
  {
    "Id":122, "CircleEventMasterId":1, "Point":160000, "ThingType":"Coin", "ThingId":0, "ThingQuantity":30000, "Order":0
  },
  {
    "Id":123, "CircleEventMasterId":1, "Point":170000, "ThingType":"Item", "ThingId":130063, "ThingQuantity":50, "Order":0
  },
  {
    "Id":124, "CircleEventMasterId":1, "Point":180000, "ThingType":"Item", "ThingId":130042, "ThingQuantity":50, "Order":0
  },
  {
    "Id":125, "CircleEventMasterId":1, "Point":190000, "ThingType":"Jewel", "ThingId":0, "ThingQuantity":200, "Order":0
  },
  {
    "Id":126, "CircleEventMasterId":1, "Point":200000, "ThingType":"Item", "ThingId":130051, "ThingQuantity":5, "Order":0
  },
  {
    "Id":127, "CircleEventMasterId":1, "Point":220000, "ThingType":"Item", "ThingId":120003, "ThingQuantity":50, "Order":0
  },
  {
    "Id":128, "CircleEventMasterId":1, "Point":240000, "ThingType":"Item", "ThingId":140000, "ThingQuantity":100, "Order":0
  },
  {
    "Id":129, "CircleEventMasterId":1, "Point":260000, "ThingType":"Item", "ThingId":130071, "ThingQuantity":1, "Order":0
  },
  {
    "Id":130, "CircleEventMasterId":1, "Point":280000, "ThingType":"Item", "ThingId":130063, "ThingQuantity":50, "Order":0
  },
  {
    "Id":131, "CircleEventMasterId":1, "Point":300000, "ThingType":"Coin", "ThingId":0, "ThingQuantity":50000, "Order":0
  },
  {
    "Id":132, "CircleEventMasterId":1, "Point":350000, "ThingType":"Item", "ThingId":130042, "ThingQuantity":50, "Order":0
  },
  {
    "Id":133, "CircleEventMasterId":1, "Point":400000, "ThingType":"Item", "ThingId":120003, "ThingQuantity":100, "Order":0
  },
  {
    "Id":134, "CircleEventMasterId":1, "Point":450000, "ThingType":"Item", "ThingId":130063, "ThingQuantity":50, "Order":0
  },
  {
    "Id":135, "CircleEventMasterId":1, "Point":500000, "ThingType":"Jewel", "ThingId":0, "ThingQuantity":300, "Order":0
  },
  {
    "Id":136, "CircleEventMasterId":1, "Point":600000, "ThingType":"Item", "ThingId":130071, "ThingQuantity":2, "Order":0
  },
  {
    "Id":137, "CircleEventMasterId":1, "Point":700000, "ThingType":"Item", "ThingId":130064, "ThingQuantity":50, "Order":0
  },
  {
    "Id":138, "CircleEventMasterId":1, "Point":800000, "ThingType":"Item", "ThingId":140000, "ThingQuantity":100, "Order":0
  },
  {
    "Id":139, "CircleEventMasterId":1, "Point":900000, "ThingType":"Item", "ThingId":130064, "ThingQuantity":50, "Order":0
  },
  {
    "Id":140, "CircleEventMasterId":1, "Point":1000000, "ThingType":"Item", "ThingId":130071, "ThingQuantity":2, "Order":0
  },
  {
    "Id":201, "CircleEventMasterId":2, "Point":1000, "ThingType":"Item", "ThingId":130062, "ThingQuantity":100, "Order":0
  },
  {
    "Id":202, "CircleEventMasterId":2, "Point":5000, "ThingType":"Item", "ThingId":110001, "ThingQuantity":5, "Order":0
  },
  {
    "Id":203, "CircleEventMasterId":2, "Point":10000, "ThingType":"Item", "ThingId":130041, "ThingQuantity":150, "Order":0
  },
  {
    "Id":204, "CircleEventMasterId":2, "Point":15000, "ThingType":"Item", "ThingId":120002, "ThingQuantity":150, "Order":0
  },
  {
    "Id":205, "CircleEventMasterId":2, "Point":20000, "ThingType":"Item", "ThingId":130062, "ThingQuantity":100, "Order":0
  },
  {
    "Id":206, "CircleEventMasterId":2, "Point":25000, "ThingType":"Item", "ThingId":110001, "ThingQuantity":5, "Order":0
  },
  {
    "Id":207, "CircleEventMasterId":2, "Point":30000, "ThingType":"Item", "ThingId":140000, "ThingQuantity":50, "Order":0
  },
  {
    "Id":208, "CircleEventMasterId":2, "Point":35000, "ThingType":"Item", "ThingId":130041, "ThingQuantity":200, "Order":0
  },
  {
    "Id":209, "CircleEventMasterId":2, "Point":40000, "ThingType":"Item", "ThingId":130051, "ThingQuantity":5, "Order":0
  },
  {
    "Id":210, "CircleEventMasterId":2, "Point":45000, "ThingType":"Item", "ThingId":130062, "ThingQuantity":150, "Order":0
  },
  {
    "Id":211, "CircleEventMasterId":2, "Point":50000, "ThingType":"Item", "ThingId":120002, "ThingQuantity":100, "Order":0
  },
  {
    "Id":212, "CircleEventMasterId":2, "Point":60000, "ThingType":"Item", "ThingId":110001, "ThingQuantity":5, "Order":0
  },
  {
    "Id":213, "CircleEventMasterId":2, "Point":70000, "ThingType":"Coin", "ThingId":0, "ThingQuantity":20000, "Order":0
  },
  {
    "Id":214, "CircleEventMasterId":2, "Point":80000, "ThingType":"Item", "ThingId":130051, "ThingQuantity":5, "Order":0
  },
  {
    "Id":215, "CircleEventMasterId":2, "Point":90000, "ThingType":"Item", "ThingId":140000, "ThingQuantity":100, "Order":0
  },
  {
    "Id":216, "CircleEventMasterId":2, "Point":100000, "ThingType":"Item", "ThingId":130062, "ThingQuantity":200, "Order":0
  },
  {
    "Id":217, "CircleEventMasterId":2, "Point":110000, "ThingType":"Item", "ThingId":120002, "ThingQuantity":150, "Order":0
  },
  {
    "Id":218, "CircleEventMasterId":2, "Point":120000, "ThingType":"Item", "ThingId":130041, "ThingQuantity":250, "Order":0
  },
  {
    "Id":219, "CircleEventMasterId":2, "Point":130000, "ThingType":"Item", "ThingId":120003, "ThingQuantity":50, "Order":0
  },
  {
    "Id":220, "CircleEventMasterId":2, "Point":140000, "ThingType":"Item", "ThingId":130042, "ThingQuantity":100, "Order":0
  },
  {
    "Id":221, "CircleEventMasterId":2, "Point":150000, "ThingType":"Item", "ThingId":140000, "ThingQuantity":100, "Order":0
  },
  {
    "Id":222, "CircleEventMasterId":2, "Point":160000, "ThingType":"Coin", "ThingId":0, "ThingQuantity":30000, "Order":0
  },
  {
    "Id":223, "CircleEventMasterId":2, "Point":170000, "ThingType":"Item", "ThingId":130063, "ThingQuantity":50, "Order":0
  },
  {
    "Id":224, "CircleEventMasterId":2, "Point":180000, "ThingType":"Item", "ThingId":130042, "ThingQuantity":150, "Order":0
  },
  {
    "Id":225, "CircleEventMasterId":2, "Point":190000, "ThingType":"Jewel", "ThingId":0, "ThingQuantity":100, "Order":0
  },
  {
    "Id":226, "CircleEventMasterId":2, "Point":200000, "ThingType":"Item", "ThingId":130051, "ThingQuantity":5, "Order":0
  },
  {
    "Id":227, "CircleEventMasterId":2, "Point":220000, "ThingType":"Item", "ThingId":120003, "ThingQuantity":50, "Order":0
  },
  {
    "Id":228, "CircleEventMasterId":2, "Point":240000, "ThingType":"Item", "ThingId":140000, "ThingQuantity":100, "Order":0
  },
  {
    "Id":229, "CircleEventMasterId":2, "Point":260000, "ThingType":"Item", "ThingId":130071, "ThingQuantity":1, "Order":0
  },
  {
    "Id":230, "CircleEventMasterId":2, "Point":280000, "ThingType":"Item", "ThingId":130063, "ThingQuantity":100, "Order":0
  },
  {
    "Id":231, "CircleEventMasterId":2, "Point":300000, "ThingType":"Coin", "ThingId":0, "ThingQuantity":50000, "Order":0
  },
  {
    "Id":232, "CircleEventMasterId":2, "Point":350000, "ThingType":"Item", "ThingId":130042, "ThingQuantity":200, "Order":0
  },
  {
    "Id":233, "CircleEventMasterId":2, "Point":400000, "ThingType":"Item", "ThingId":130051, "ThingQuantity":5, "Order":0
  },
  {
    "Id":234, "CircleEventMasterId":2, "Point":450000, "ThingType":"Item", "ThingId":120003, "ThingQuantity":100, "Order":0
  },
  {
    "Id":235, "CircleEventMasterId":2, "Point":500000, "ThingType":"Item", "ThingId":130063, "ThingQuantity":50, "Order":0
  },
  {
    "Id":236, "CircleEventMasterId":2, "Point":600000, "ThingType":"Item", "ThingId":130043, "ThingQuantity":50, "Order":0
  },
  {
    "Id":237, "CircleEventMasterId":2, "Point":700000, "ThingType":"Jewel", "ThingId":0, "ThingQuantity":150, "Order":0
  },
  {
    "Id":238, "CircleEventMasterId":2, "Point":800000, "ThingType":"Item", "ThingId":130071, "ThingQuantity":2, "Order":0
  },
  {
    "Id":239, "CircleEventMasterId":2, "Point":900000, "ThingType":"Item", "ThingId":130064, "ThingQuantity":50, "Order":0
  },
  {
    "Id":240, "CircleEventMasterId":2, "Point":1000000, "ThingType":"Item", "ThingId":140000, "ThingQuantity":100, "Order":0
  },
  {
    "Id":241, "CircleEventMasterId":2, "Point":1250000, "ThingType":"Item", "ThingId":130064, "ThingQuantity":50, "Order":0
  },
  {
    "Id":242, "CircleEventMasterId":2, "Point":1500000, "ThingType":"Item", "ThingId":130071, "ThingQuantity":2, "Order":0
  },
  {
    "Id":243, "CircleEventMasterId":2, "Point":1750000, "ThingType":"Item", "ThingId":130043, "ThingQuantity":100, "Order":0
  },
  {
    "Id":244, "CircleEventMasterId":2, "Point":2000000, "ThingType":"Jewel", "ThingId":0, "ThingQuantity":200, "Order":0
  },
  {
    "Id":245, "CircleEventMasterId":2, "Point":2500000, "ThingType":"Item", "ThingId":150000, "ThingQuantity":10, "Order":0
  },
  {
    "Id":246, "CircleEventMasterId":2, "Point":3000000, "ThingType":"Jewel", "ThingId":0, "ThingQuantity":200, "Order":0
  },
  {
    "Id":247, "CircleEventMasterId":2, "Point":4000000, "ThingType":"Item", "ThingId":150000, "ThingQuantity":15, "Order":0
  },
  {
    "Id":248, "CircleEventMasterId":2, "Point":5000000, "ThingType":"Jewel", "ThingId":0, "ThingQuantity":250, "Order":0
  },
  {
    "Id":249, "CircleEventMasterId":2, "Point":6000000, "ThingType":"Item", "ThingId":130071, "ThingQuantity":2, "Order":0
  },
  {
    "Id":250, "CircleEventMasterId":2, "Point":7000000, "ThingType":"Item", "ThingId":150000, "ThingQuantity":20, "Order":0
  },
  {
    "Id":251, "CircleEventMasterId":2, "Point":8000000, "ThingType":"Jewel", "ThingId":0, "ThingQuantity":300, "Order":0
  },
  {
    "Id":252, "CircleEventMasterId":2, "Point":9000000, "ThingType":"Item", "ThingId":150000, "ThingQuantity":25, "Order":0
  },
  {
    "Id":253, "CircleEventMasterId":2, "Point":10000000, "ThingType":"Item", "ThingId":130071, "ThingQuantity":3, "Order":0
  },
  {
    "Id":301, "CircleEventMasterId":3, "Point":1000, "ThingType":"Item", "ThingId":130062, "ThingQuantity":100, "Order":0
  },
  {
    "Id":302, "CircleEventMasterId":3, "Point":5000, "ThingType":"Item", "ThingId":110001, "ThingQuantity":5, "Order":0
  },
  {
    "Id":303, "CircleEventMasterId":3, "Point":10000, "ThingType":"Item", "ThingId":130041, "ThingQuantity":150, "Order":0
  },
  {
    "Id":304, "CircleEventMasterId":3, "Point":15000, "ThingType":"Item", "ThingId":120002, "ThingQuantity":150, "Order":0
  },
  {
    "Id":305, "CircleEventMasterId":3, "Point":20000, "ThingType":"Item", "ThingId":130062, "ThingQuantity":100, "Order":0
  },
  {
    "Id":306, "CircleEventMasterId":3, "Point":25000, "ThingType":"Item", "ThingId":110001, "ThingQuantity":5, "Order":0
  },
  {
    "Id":307, "CircleEventMasterId":3, "Point":30000, "ThingType":"Item", "ThingId":140000, "ThingQuantity":50, "Order":0
  },
  {
    "Id":308, "CircleEventMasterId":3, "Point":35000, "ThingType":"Item", "ThingId":130041, "ThingQuantity":200, "Order":0
  },
  {
    "Id":309, "CircleEventMasterId":3, "Point":40000, "ThingType":"Item", "ThingId":130051, "ThingQuantity":5, "Order":0
  },
  {
    "Id":310, "CircleEventMasterId":3, "Point":45000, "ThingType":"Item", "ThingId":130062, "ThingQuantity":150, "Order":0
  },
  {
    "Id":311, "CircleEventMasterId":3, "Point":50000, "ThingType":"Item", "ThingId":120002, "ThingQuantity":100, "Order":0
  },
  {
    "Id":312, "CircleEventMasterId":3, "Point":60000, "ThingType":"Item", "ThingId":110001, "ThingQuantity":5, "Order":0
  },
  {
    "Id":313, "CircleEventMasterId":3, "Point":70000, "ThingType":"Coin", "ThingId":0, "ThingQuantity":20000, "Order":0
  },
  {
    "Id":314, "CircleEventMasterId":3, "Point":80000, "ThingType":"Item", "ThingId":130051, "ThingQuantity":5, "Order":0
  },
  {
    "Id":315, "CircleEventMasterId":3, "Point":90000, "ThingType":"Item", "ThingId":140000, "ThingQuantity":100, "Order":0
  },
  {
    "Id":316, "CircleEventMasterId":3, "Point":100000, "ThingType":"Item", "ThingId":130062, "ThingQuantity":200, "Order":0
  },
  {
    "Id":317, "CircleEventMasterId":3, "Point":110000, "ThingType":"Item", "ThingId":120002, "ThingQuantity":150, "Order":0
  },
  {
    "Id":318, "CircleEventMasterId":3, "Point":120000, "ThingType":"Item", "ThingId":130041, "ThingQuantity":250, "Order":0
  },
  {
    "Id":319, "CircleEventMasterId":3, "Point":130000, "ThingType":"Item", "ThingId":120003, "ThingQuantity":50, "Order":0
  },
  {
    "Id":320, "CircleEventMasterId":3, "Point":140000, "ThingType":"Item", "ThingId":130042, "ThingQuantity":100, "Order":0
  },
  {
    "Id":321, "CircleEventMasterId":3, "Point":150000, "ThingType":"Item", "ThingId":140000, "ThingQuantity":100, "Order":0
  },
  {
    "Id":322, "CircleEventMasterId":3, "Point":160000, "ThingType":"Coin", "ThingId":0, "ThingQuantity":30000, "Order":0
  },
  {
    "Id":323, "CircleEventMasterId":3, "Point":170000, "ThingType":"Item", "ThingId":130063, "ThingQuantity":50, "Order":0
  },
  {
    "Id":324, "CircleEventMasterId":3, "Point":180000, "ThingType":"Item", "ThingId":130042, "ThingQuantity":150, "Order":0
  },
  {
    "Id":325, "CircleEventMasterId":3, "Point":190000, "ThingType":"Jewel", "ThingId":0, "ThingQuantity":100, "Order":0
  },
  {
    "Id":326, "CircleEventMasterId":3, "Point":200000, "ThingType":"Item", "ThingId":130051, "ThingQuantity":5, "Order":0
  },
  {
    "Id":327, "CircleEventMasterId":3, "Point":220000, "ThingType":"Item", "ThingId":120003, "ThingQuantity":50, "Order":0
  },
  {
    "Id":328, "CircleEventMasterId":3, "Point":240000, "ThingType":"Item", "ThingId":140000, "ThingQuantity":100, "Order":0
  },
  {
    "Id":329, "CircleEventMasterId":3, "Point":260000, "ThingType":"Item", "ThingId":130071, "ThingQuantity":1, "Order":0
  },
  {
    "Id":330, "CircleEventMasterId":3, "Point":280000, "ThingType":"Item", "ThingId":130063, "ThingQuantity":100, "Order":0
  },
  {
    "Id":331, "CircleEventMasterId":3, "Point":300000, "ThingType":"Coin", "ThingId":0, "ThingQuantity":50000, "Order":0
  },
  {
    "Id":332, "CircleEventMasterId":3, "Point":350000, "ThingType":"Item", "ThingId":130042, "ThingQuantity":200, "Order":0
  },
  {
    "Id":333, "CircleEventMasterId":3, "Point":400000, "ThingType":"Item", "ThingId":130051, "ThingQuantity":5, "Order":0
  },
  {
    "Id":334, "CircleEventMasterId":3, "Point":450000, "ThingType":"Item", "ThingId":120003, "ThingQuantity":100, "Order":0
  },
  {
    "Id":335, "CircleEventMasterId":3, "Point":500000, "ThingType":"Item", "ThingId":130063, "ThingQuantity":50, "Order":0
  },
  {
    "Id":336, "CircleEventMasterId":3, "Point":600000, "ThingType":"Item", "ThingId":130043, "ThingQuantity":50, "Order":0
  },
  {
    "Id":337, "CircleEventMasterId":3, "Point":700000, "ThingType":"Jewel", "ThingId":0, "ThingQuantity":150, "Order":0
  },
  {
    "Id":338, "CircleEventMasterId":3, "Point":800000, "ThingType":"Item", "ThingId":130071, "ThingQuantity":2, "Order":0
  },
  {
    "Id":339, "CircleEventMasterId":3, "Point":900000, "ThingType":"Item", "ThingId":130064, "ThingQuantity":50, "Order":0
  },
  {
    "Id":340, "CircleEventMasterId":3, "Point":1000000, "ThingType":"Item", "ThingId":140000, "ThingQuantity":100, "Order":0
  },
  {
    "Id":341, "CircleEventMasterId":3, "Point":1250000, "ThingType":"Item", "ThingId":130064, "ThingQuantity":50, "Order":0
  },
  {
    "Id":342, "CircleEventMasterId":3, "Point":1500000, "ThingType":"Item", "ThingId":130071, "ThingQuantity":2, "Order":0
  },
  {
    "Id":343, "CircleEventMasterId":3, "Point":1750000, "ThingType":"Item", "ThingId":130043, "ThingQuantity":100, "Order":0
  },
  {
    "Id":344, "CircleEventMasterId":3, "Point":2000000, "ThingType":"Jewel", "ThingId":0, "ThingQuantity":200, "Order":0
  },
  {
    "Id":345, "CircleEventMasterId":3, "Point":2500000, "ThingType":"Item", "ThingId":150000, "ThingQuantity":10, "Order":0
  },
  {
    "Id":346, "CircleEventMasterId":3, "Point":3000000, "ThingType":"Jewel", "ThingId":0, "ThingQuantity":200, "Order":0
  },
  {
    "Id":347, "CircleEventMasterId":3, "Point":4000000, "ThingType":"Item", "ThingId":150000, "ThingQuantity":15, "Order":0
  },
  {
    "Id":348, "CircleEventMasterId":3, "Point":5000000, "ThingType":"Jewel", "ThingId":0, "ThingQuantity":250, "Order":0
  },
  {
    "Id":349, "CircleEventMasterId":3, "Point":6000000, "ThingType":"Item", "ThingId":130071, "ThingQuantity":2, "Order":0
  },
  {
    "Id":350, "CircleEventMasterId":3, "Point":7000000, "ThingType":"Item", "ThingId":150000, "ThingQuantity":20, "Order":0
  },
  {
    "Id":351, "CircleEventMasterId":3, "Point":8000000, "ThingType":"Jewel", "ThingId":0, "ThingQuantity":300, "Order":0
  },
  {
    "Id":352, "CircleEventMasterId":3, "Point":9000000, "ThingType":"Item", "ThingId":150000, "ThingQuantity":25, "Order":0
  },
  {
    "Id":353, "CircleEventMasterId":3, "Point":10000000, "ThingType":"Item", "ThingId":130071, "ThingQuantity":3, "Order":0
  }
]
