[
  {
    "Id":20001, "Category":1, "BonusAttribute":1, "Title":"god is no /w/ here", "ExchangeShopMasterId":20001, "EventPointItemMasterId":420001, "StartDate":"2023-07-31 17:00:00", "EndDate":"2023-08-08 22:00:00", "ForceEndDate":"2023-08-10 17:00:00"
  },
  {
    "Id":20002, "Category":3, "BonusAttribute":2, "Title":"エレクトリック・サマー・バカンス", "ExchangeShopMasterId":20002, "EventPointItemMasterId":420002, "StartDate":"2023-08-10 17:00:00", "EndDate":"2023-08-18 22:00:00", "ForceEndDate":"2023-08-20 17:00:00"
  },
  {
    "Id":20003, "Category":4, "BonusAttribute":2, "Title":"隠し味はひとさじのユーモア", "ExchangeShopMasterId":20003, "EventPointItemMasterId":420003, "StartDate":"2023-08-20 17:00:00", "EndDate":"2023-08-28 22:00:00", "ForceEndDate":"2023-08-31 17:00:00"
  },
  {
    "Id":20004, "Category":1, "BonusAttribute":3, "Title":"泡沫烟花", "ExchangeShopMasterId":20004, "EventPointItemMasterId":420004, "StartDate":"2023-08-31 17:00:00", "EndDate":"2023-09-08 22:00:00", "ForceEndDate":"2023-09-10 17:00:00"
  },
  {
    "Id":20005, "Category":3, "BonusAttribute":1, "Title":"脚光が照らすこれから", "ExchangeShopMasterId":20005, "EventPointItemMasterId":420005, "StartDate":"2023-09-10 17:00:00", "EndDate":"2023-09-18 22:00:00", "ForceEndDate":"2023-09-20 17:00:00"
  },
  {
    "Id":20006, "Category":3, "BonusAttribute":3, "Title":"歌川高校体育祭！　～応援団長の一日～", "ExchangeShopMasterId":20006, "EventPointItemMasterId":420006, "StartDate":"2023-09-20 17:00:00", "EndDate":"2023-09-28 22:00:00", "ForceEndDate":"2023-09-30 17:00:00"
  },
  {
    "Id":20007, "Category":1, "BonusAttribute":4, "Title":"FAIR IS FOUL, AND FOUL IS FAIR", "ExchangeShopMasterId":20007, "EventPointItemMasterId":420007, "StartDate":"2023-09-30 17:00:00", "EndDate":"2023-10-08 22:00:00", "ForceEndDate":"2023-10-10 17:00:00"
  }
]